backup_dataset/__init__.py
backup_dataset/clas_paperwithcode/__init__.py
backup_dataset/clas_paperwithcode/dataset.py
backup_dataset/drcdtag/__init__.py
backup_dataset/drcdtag/dataset.py
backup_dataset/gen_humor/__init__.py
backup_dataset/gen_humor/dataset.py
backup_dataset/gen_mt/__init__.py
backup_dataset/gen_mt/dataset.py
backup_dataset/gen_poetry/__init__.py
backup_dataset/gen_poetry/dataset.py
backup_dataset/multiqa/__init__.py
backup_dataset/multiqa/dataset.py
nlprep/__init__.py
nlprep/file_utils.py
nlprep/main.py
nlprep/middleformat.py
nlprep/datasets/__init__.py
nlprep/datasets/clas_cosmosqa/__init__.py
nlprep/datasets/clas_cosmosqa/dataset.py
nlprep/datasets/clas_csv/__init__.py
nlprep/datasets/clas_csv/dataset.py
nlprep/datasets/clas_lihkgcat/__init__.py
nlprep/datasets/clas_lihkgcat/dataset.py
nlprep/datasets/clas_mathqa/__init__.py
nlprep/datasets/clas_mathqa/dataset.py
nlprep/datasets/clas_snli/__init__.py
nlprep/datasets/clas_snli/dataset.py
nlprep/datasets/clas_udicstm/__init__.py
nlprep/datasets/clas_udicstm/dataset.py
nlprep/datasets/gen_dream/__init__.py
nlprep/datasets/gen_dream/dataset.py
nlprep/datasets/gen_lcccbase/__init__.py
nlprep/datasets/gen_lcccbase/dataset.py
nlprep/datasets/gen_masklm/__init__.py
nlprep/datasets/gen_masklm/dataset.py
nlprep/datasets/gen_pttchat/__init__.py
nlprep/datasets/gen_pttchat/dataset.py
nlprep/datasets/gen_squadqg/__init__.py
nlprep/datasets/gen_squadqg/dataset.py
nlprep/datasets/gen_storyend/__init__.py
nlprep/datasets/gen_storyend/dataset.py
nlprep/datasets/gen_sumcnndm/__init__.py
nlprep/datasets/gen_sumcnndm/dataset.py
nlprep/datasets/gen_wmt17news/__init__.py
nlprep/datasets/gen_wmt17news/dataset.py
nlprep/datasets/qa_zh/__init__.py
nlprep/datasets/qa_zh/dataset.py
nlprep/datasets/tag_cged/__init__.py
nlprep/datasets/tag_cged/dataset.py
nlprep/datasets/tag_clner/__init__.py
nlprep/datasets/tag_clner/dataset.py
nlprep/datasets/tag_cnername/__init__.py
nlprep/datasets/tag_cnername/dataset.py
nlprep-0.2.1.dist-info/LICENSE
nlprep-0.2.1.dist-info/METADATA
nlprep-0.2.1.dist-info/WHEEL
nlprep-0.2.1.dist-info/entry_points.txt
nlprep-0.2.1.dist-info/top_level.txt
nlprep-0.2.1.dist-info/RECORD
