Metadata-Version: 2.1
Name: nlprep
Version: 0.2.1
Summary: Download and pre-processing data for nlp tasks
Home-page: https://github.com/voidful/nlprep
Author: Voidful
Author-email: voidful.stack@gmail.com
License: UNKNOWN
Keywords: nlp tfkit classification generation tagging deep learning machine reading
Platform: UNKNOWN
License-File: LICENSE
Requires-Dist: boto3
Requires-Dist: filelock
Requires-Dist: requests
Requires-Dist: tqdm (>=4.27)
Requires-Dist: opencc-python-reimplemented
Requires-Dist: nlp2 (>=1.8.27)
Requires-Dist: pandas-profiling (>=2.8.0)
Requires-Dist: datasets
Requires-Dist: phraseg (>=1.1.8)
Requires-Dist: transformers (>=3.3.0)
Requires-Dist: inquirer
Requires-Dist: BeautifulSoup4
Requires-Dist: lxml
